{
    "book_name": "تحفة العروس و متعة النفوس",
    "page_number": 74,
    "text_chunk": "تحفة العروس ومتعة النفوس  وقال الأصمعي في قول كعب بن زهير خرك اخوها ابوها في مهنه وعمهاخائها قواه شمليل قال هذه داقة كريمة مداخلة النسب لشرفها فانكر ذلك ابو المكارم على الاصمعي وقتال الم يعلم قائل هذا أن تداخل النسب ومقاربته مما يضعف الناقة  وذكر البكري في اللآلي عند قول الأعرابي وما قرقمني إلا الكرم قال يعني أن أباه طلب المناكع الكريمة في أصله فجاءه ولده يسبب اذلك ضاويا انتهى كلام البكري  قال غييه وسبب هذا أن ابئة العم وتحوها من ذوي القرابة القريبة لا تقع عن نفس الزوح موقع الغريبة إما لالفته لها ودوام النظر إليها إذا كانت كذلك وإما لانه يقع بينه وبينها من الحشمة والخجل ما تكسل به وتضعف شهوته والولد لا يكمل خلقه وتتم قوته إلا بتمام الشهوة وقوتهاء ولهذا قالوا من استحيا من امراته لم ينجب  ابو الفرج في الاغائي قال جاء منظور بن زبان الفزاري إلى حسن بن حسن  وهو جده  القبية ص   م   الصارة الأية عي موجودة يم والشلوي النحيه المي الا العبة   الم اد لسري الأعنيع  سور وبال لوازي طيحي الفاني اج الس    الحسن سن االحسن بن علي بن ابي لت ",
    "label": 0,
    "confidence": 0.6666666666666666
}