{
    "book_name": "الغداء العاري",
    "page_number": 63,
    "text_chunk": "المخربون المراهقون من جماعة الروك أند رول يحتلون شوارع العالم يقتحمون متحف اللوفر ويرشقون وجه الموناليزا بالحمض يفتحون حدائق الحيوانات السجون المصحات النفسية يفيجرون أنابيب المياه المركزية بمطارق هوائية يحرون أرضية المراحيض في طائرين المسافرين يفجمرون المنارات يبردون كوابل المصاعد ويحولوتها إلى خيوط رفيعة يوصلون أنابيب الصرف الصحي بأنبوب ميا الشرب يلقون بأسماك القرش وأسماك الرقيطة والأنقليس والكانديرو في برك للسباحة الكانديرو هو سمك يشيه الأنقليس يبلغ طوله خمسة ستتيمترات وعرضه نصف ستتيمتره يتحاز للأنهار سئة الضيت في حوض الأمازون يثب على أيرك ثقب مؤخرتك أو على فرج امرأة في حال غياب بديل أفضل ويثبت نفسه هناك بمساعدة أشواكه ما من أحد يعرف السبب لأنه ما من أحد بحث الكانديرو في بيثته الطبيعية بالزي البحري يطلقون سفينة كوين ماري بسرعة صوب ميناء نيويورك  يلعبون لعبة القميضة مع طائرات",
    "label": 0,
    "confidence": 1.0
}