{
    "book_name": "الخبز الحافي",
    "page_number": 102,
    "text_chunk": "جعلوني أوقع بإبيامي ورقة أخمرى مكتربة أعطيت اسمي لاحدهما وسلم لي نقودتي وسزامي وسيري حذائي ذكرت ماذا كتبرا أيضا عن في هذه الررقة في استطاعتهم أن يكتبوا عني ما يشاؤون ما دمت الا أستطيع أن أقرأ ما هو مكتوب في تلك الورقة لا أجرؤ أن أطلب  متهم أن يأنوا في يمن يقرأها لي قبل أن أوقعها قد يييدوني إلى السجن إذا أنا طلبت منهم ذلك قال في شرطي الحراسة  إتصرف الآن رن جرس المنبه مدت يدي في القلام رأوقفت مضت وأشملت خرجت من لتب ناميا نعي وغياني  عند اباب اصطدمت الضوء كانت الخاسة صاحا النيم ما زال لذيذا في عيو بعد يشخص اعتذرت أ دذمني فامتطدمت مع الجدار ساعة ستدخل الباخرة نظرت إلى نعيمة النائمة بلا هموم أكره ا ا العيش مع امرأة لا تشفل نفسها بشيء لا عمل ها سري أن تفتح لي شف قدايك يااعاد الكمار أو لغيري فخذيها بوشتا تروج فوزية رما نطن أنني أيضا سأتزوجها طني وائمنيت لأعيد إلى قدي القردة التي الس الكرت لا كلهن حكذا لا يك الراحد بيدأ اليش مع إحداهن حي توقعه في يمكن أن يسب هكذاء فى هذا المكان سوى الشرطة فخ انتفخ البطن إنهن لا يتخذن أي احتياط عمدا لكن ليس للدي في الحارج عقدت سبرى حذائي وحزامي  كان يوم بارا ما أخسر إذا وقعت في فخها فسأهجر هذه المدينة إلى مدينة أخري ومشمسا تنفست بعمق ومشيث وأتشركها تسقط في نخها لبست ثياي وملت قفة السلعة اطفي    الضوء  خرجت بهدوم في السوق اكبير دلت مطما لبيع البيصر وأنا أفكر في التقود لني تركه لي القندوري عد صصاحب قبرةالرقاصة في الطاب الأسفل غسلت وجي جا يارد كالتج  أيققلت المارس ابحذر شرب بيده في الهواء كعلاته عندما يكون نائا ويوقظه أحدء النه يشعر أنه دائامهاجم  نظر إل جاحظ العينين دون أن يتكلم عيد السلام أنا شكري سأخرج قم لتقل اباب أرسل شهيقا ثم نزل من فراشه متعبا تقدمثي وفنح اباب الحارجي  فاحت منه رائحة حمر قال لي وأنا أخوج  اله يعاوتك  لفق",
    "label": 0,
    "confidence": 0.6666666666666666
}