{
    "book_name": "لقيطة إسطنبول",
    "page_number": 60,
    "text_chunk": "لم تكمل روز جملتها لآن فكرة خبيثة طرآت لها على الفور كان لون إشارة المرور قد تحؤل إلى الأخضرء وبدأت السيارات أمامها تتقدمء وأطلقت الشاحتة وراءها زمورا لكن روز ظلت واقفة في مكانها ولم تتحرك كانت المخئلة لذيذة إلى درجة أنها لم تستطع أن تتحرك وبدأت نتداعى إلى رأسها صور شتى فيما أضاءت عيناها بشعاع من الغضب الخالص بزاوية متحرفة كان هذا في واقع الأمرء ثالث تأثير جانبي نتيجة الإحساس بالقنوط المزمن بعد الطلاق فهو لا يجملك تتكلمين مع نفسك ومشاكة الآخرين فقطء بل يجعلك أيضا لا عفلانية وغير منطقية فما إن تشعر المرأة بالسخط المبررء حتى ينقلب العالم رأسا على عقب ويصبح اللامنطقي منطقيا تعاما",
    "label": 0,
    "confidence": 1.0
}