{
    "book_name": "سقوط الإمام",
    "page_number": 39,
    "text_chunk": "الهتاف يدوي الله معك يرج أذتيهاء يتدلى منها قرط الماس يهتر مع دوي الصوت ومن حوله الإشعاع ملايين الأضواء وعنقها الأبيض كالرخام يرتج ومن حوله عقد اللؤلق الحر خمسة أدوار وفوق صدرها الوسام على شكل بروش يعكس الضوء كقرص الشمس وأصابعها تحوطها الخواتم والفصوص كالنجوم تملأ الكون بالضياء وهي واقفة في شرفة الحريم ومن حولها كبيرات نساء الدولة يرتدين وجوما مشدودة وثيابا حريرية مرتخية وعوراتهن مختفية تحت حجاب مستورد من أجود الأنواع وهي واقفة في الشرفة عنقها مشرئب نحو زوجها الإمام وعنقه مشرئب نحو الله قلبها تحت ضلوعها يدق وفوق القلب تحت النهد صليب محفور في الجلد فوقه السيح مدقوق بالسامير رفعت يدها ورسمت فوق صدرها الثالوث الأب والابن والروح القدس احفظيه من أعدائه يا ستنا العذراء أستغفر الله احفظه يا رب ويا رسول اله فأنا تركت المسيح من أجل الحب تركت اسمي واسم أبي أهلي وبلدي ودينيء وألقيت بهم جميعا في البحر كنت مرهقة أغسل الصحون وأتتفس في القطارات تحت الأرض هواء تنسه قبلي اللايين أبتسم في الوجوه والوجوه لا تبتسم لي أذهب إلى الكنيسة كل يوم أحد وأدعو المسيح ليتقذني من الفقر عشرون عاما ولم ينقذني الأب أ الابن أو الروح القدس ثم جاء الإمام وأنقذني رأيته جالسا فوق العرش ووقعت من أول نظرة في الحب حملني بين ذراعيه وارتفع رأسي في السماء عرفت الجنة فوق الأرض آمنت بالله والرسول حدائق وقصور وخدم وحشم وأنهار من العسل والخمر أرفع رأسي والرءوس من حولي تنخفض يبتسمون في وجهي ولا أبتسم أمشي أمام الوزراء ومن حولي الأضواء أفتتح المستشفيات وملاجئ الأطفال اسمي في التاريخ محفور بحروف من النور زوجة الإمام ليس لها شريكة فوق العرش ولا تعلو عليها امرأة في جمال أو علم أو جاه",
    "label": 0,
    "confidence": 1.0
}