{
    "book_name": "يوليسيس",
    "page_number": 155,
    "text_chunk": " إلى جانب رافعات رصيف ميناء السير ججون روجوسن  سار المستر بلوم برزانة عابرا زقسان وندمل وثسركة ليك لعسصر بزور الكتسان ودائرة البسريد واللاسلكي كان بإمكاني استعمال ذاك العنران كذلك وعابر مقر البحارة دار عن ضوضا ءات صباح رصيف الميناء وسار في شارع لايم عند سباتي بريديأ صبي يجمع النفايات متكاسلا سطلته التي يجمع فيها النفابات يسك بها بسلسلة مدخن عقب سيكارة معلوسا صبية أصغر منه على جبينها تدب أكزيما عاينته ممسكة بكسل لعبتها من نفاية طوق مررض تشد بها براميل الحمور اقل له إذ دحن فإنه لن بكبر أوه دعها حياته ليست بتلك الرفاهية منتظرا خارج الحانات ليجلب بابا إلى البيت تعال إلى ماماء با بابا ساعة قائرة ما من زماتن كشيرين هناك اجنتاز شارع تاوتز إندء مار بوجد البشل  الكالع إل انعم بيت أل ألف بيت ومجتازآ محل ونيكول لنقل ا موتى ستكون في الساعة الحاديقعشرة وقت كاف أظن أن وكورني كليهرء هو الذي حصل الوظيفة ل أونبل راح بغئي وهو مفمض العسينين كورني  النقى بها في يومرما بلمتنزها في الظلام با للمتعة مخير للشرطة اسمها وعنواتها أعطتهما بأغنية تورالوم تورالوم تي  آه بالتأكيد حصلها أدفنه بسعر رخيص في ما الذي قد",
    "label": 0,
    "confidence": 0.6666666666666666
}