{
    "book_name": "خماسية مدن الملح",
    "page_number": 687,
    "text_chunk": "وعاد ابن شاهين شابا في حربه وقناعاته وفي لياليه أيضا لم يكن بحاجة إلى من يحرضه إلى من يقول له ماذا يجب أن يفعل والحكيم بعيد يراقب يسمع أما موران التي كانت تحب المطر والحرب فقد استعاضت عن تأخر الأمطار هذه السنة بمشاهدة صراع الديكة كان الصراع يجري في كل وقت وفي كل مكان العجرمي لا يعرف الألف من العصا وإذا ناقصه شيء جلال على ظهره وتقول له حي ابن شاهين خبلته خصيانه وبعد ما لهف الدنيا يريد يلهف الآخرة لكن يخسا قولوا للعور أخاف يصير الدرب فوقاني ارموا له حذيانه وما عليكم الحمار يدل مربطه وقولوا للشويهين الحية ما تنحط بالحثل وإذا دفت يشوف ونشوف العجرمي يقول عني حية قولوا له الحية التي ترعى وتفري أحسن من حيات التبن",
    "label": 0,
    "confidence": 0.6666666666666666
}