{
    "book_name": "بنات حواء الثلاث",
    "page_number": 471,
    "text_chunk": "تعالي إلى عرفي أدركت أنه كان يعني بذلك أن ما من شيء ممير فما يعنيه بعر هو تلك القاعات التي ألقى فيها محاضراته في الفصل الدراسي المنصرم لكن على ازعم من ذلك لم تكن ملاحظته ملاحظة عابرة أو اعنيادية رت في أعماقها انفعالات مفاجئة لها فقد قال لها إنها مميزة مميزة جدا في وسعه أن يرى في أعماقها ما لم يستطع أحد غيره أن يراه وفي الوقت الذي كانت تقف فيه هناك بلا حراكء ومستغرقة في التفكبر انضح لها كل شيء وضوحا جلياء إذ تبلورت آخر قطرة أمام كل توثعاتهاء وكل آمالها وفي حين عادت أدراجها إلى حيث الضيوك كانت قد اقتنعت بأن أستاذها أيضا يكن لها مشاعر عاطفية",
    "label": 0,
    "confidence": 0.6666666666666666
}