{
    "book_name": "اقنعة جنسية",
    "page_number": 36,
    "text_chunk": "ويعد الجهاز التتاسلي للمرأة الذي ما يزال يساء فهمه أكثر تعقيدا بكثير من الجهاز التتاسلي للرجل فجميع الأشياء يمكن أن تمضي على نحو خطاء أو تسبب مشقةء إذا هي مضت في طريقها الصحيح فالمرأة الغربية في علافة عذاب مع جسدها البيولوجية الطبيعية تمثل معاناة بالنسبة لهاء والصحة مرضا عسر الطمث وفقا للجدل السائد هو مرض الحضارة حيث لم تسجل النساء في الثقافات القبلية سوى شكاوى ضئيلة من الطمث أما المرأة فتتمتع في الحياة اقبلية بمكانة ممتدة أو جماعية فالديانةالقبلية تمد الطبيعق وتخضع لها لكننا في المجتمع الغربي المتقدم الذي يحاول تحسين الطبيعة أو تجاوزهاء ويتمشك بالفردية وإثبات الذات كنموذج في هذا المجتمع تحديداء نجد الحقائق الساطعة لحالة المرأة تظهر بوضوح مؤلم فكلما سعت المرأة إلى تحفيق هوية خاصة واستقلاكة شخصياء طورت من خيالها وأصبح نضالها مع الطبيعة أكثر شراسة أي مع قوانين جسدها الطبيعية الجسدية الحرون فتمعن الطبيعة بدورها في إنزال العقاب بهاء وكأنها تقول لا تجرؤين أن تكوني حرة جسدك ليس ملكا لك",
    "label": 0,
    "confidence": 0.6666666666666666
}