{
    "book_name": "نقد العقل العربي",
    "page_number": 52,
    "text_chunk": "وأغرب ما في هذا الإهمال أن الجابري كان حصر بنفسه مرجعيته فيما يتعلق بتاريخ اللامعقول بهذين الباحثين المتجايلين بويش    وفستوجبير    قفي معرض شكواه من أن اتاريخع اللامعقول العقلي في الثقافة العربية الاسلامية هو أكثر ما يهمله تاريخ الفلسفة في الاسلام وما يسكت عنه تاريخ الفلسفة الرسمي الأوروياوي التزعة بتساءل إلى أين ستتجه وجوايا عن هذا التساؤل بضيف حال من حسن حظنا أن أبحاثا حديثة نسبيء تتتمي رسميا في الثقافة الأوروبية إلى تاريخ الاديان  يتعلق الآمر أساسا بدراسة فستوجيير عن الهرمسية ودراسة بويش عن الغنوصية  تسعفنا بعض الشيء فيما نحن بصدد البحث عنه  فهي تقدم لنا من جهة دراسة عللمية وافبة عبن الهرمسية وتاريخ تشكلها ومضمرنها الديني والفلسفي العلمي كما تضع أمامنا من جهة  تستخدم هنا اتير هنا المعنى المفهومي الذي أعطهء إيه لباحث العراقي سيلو الجميل",
    "label": 0,
    "confidence": 1.0
}