{
    "book_name": "خماسية مدن الملح",
    "page_number": 1791,
    "text_chunk": "بعد أن تبادل الأخوة النظرات وكانت تمتلئ بالتحدي والخوف مقاء وحين بدأت الأجساد تنحرك وقد زايلها بعض التوتر بدأ السلطان بشرح الكثير من التفاصيل المتعلقة بما حصلء وما أجراه من اتصالات وما وصلت إليه من معلومات ولم يخل كلامه من التأكيد مرات عديدة على المخاطر التي تتعرض لها السلطنة وضرورة اتخاذ الإجراءات اللازمة للمواجهة خاصة وأن هناك معلومات مؤكدة تشير إلى احتمال تدبير مؤامرات والاتصال بالمعارضين وتحريض السكان لذلك يجب الحذر والحيطة وإلى إحداث تغييرات تتناسب مع المرحلة الجديدة بما في ذلك الاستغناء عن عدد من الوزراء واستبدالهم بغيرهم وضرورة أن يكون أحد الأمراء وزيرا للداخلية وآخر للمالية وأن يكون ثالنا للدفاع",
    "label": 0,
    "confidence": 0.6666666666666666
}