{
    "book_name": "اقنعة جنسية",
    "page_number": 680,
    "text_chunk": "إن ثيمة إخضاع الذكر لسلطة الأنثى نجدها أكثر تطرا ووعيا عند سويدبرن أكثر من أي فنان كبير آخر فالحياة والعمل متعاتقان أو متداخلان في بعضهما بعضاء كما هو الحال مع الماركيز دي ساد حيث إن سوينبرن على ما يبدوء كان مازوخيا بالمعنى الصارم للكلمة أي أنه أحب أن يجلد بالسياط على يد النساء وقد زار مواخير وبيوت دعارة من أجل هذا الغرض وإني لأقاوم الإدراك العام المتمثل في أن الساديين والمازوخبين غير متوافقين فهم مثل العاهرات اللخبيرات يرون عبر أفنعة المجتمع الجنسية وعلى خلاف العاهرات افإتهم يرغبون في الطبيعة البائدة ومازوخية سوينرن كان لها معنى ميتافيزيقي فالجبلد الترفيهي بالسياط كان مرتبطا لديه بعلم نشوء الكون الشعري الذي يعيد الأم الكبرى إلى السلطة وقد كان الجلد الذاتي جوهريا في عقائد الأم القديمة فالكلمات التي تعني التجلد والضرب بالسياط  وعصنهوك رعسل اعدعد كلمة اندهع مطا تمني درس الحب باستخدام مطرقة الستابل التي تطرق بها الستابل لاستخراج الحبوب من الكلمة اللاثينبة نم أو اتنالامج ك سوط كرياج وعند سوينبرن يحاكى اليلد الطقوسي العمليات العامة للزراعة والسادومازوخية تعد عقيدة طبيعية منحرفة وبنسليمه فاه إلى المجلد بالسياط فإن سوينبرن قد شل أو صاغ مسرحا العلاقات الجنسية الهيراركية لعالم تصنعه وتنقطه قوة أنثوية العقل والجسد واللذة والألء والأم والان تم إعادة اتحادها كلها في احتفال جنسي قديم بائد",
    "label": 0,
    "confidence": 1.0
}