{
    "book_name": "اقنعة جنسية",
    "page_number": 591,
    "text_chunk": "إن رواية القتة ذات الأعين الذهبية ورواية سيرافيتاء تردان على بعضهما بعضاء تعكسان نجمتيهما المخين وبنهايتها الانحطاطية لرواي الفتاق التي تعد رواية لا أخلاقية يتم صف مختتتين أو مختتين بطريقة دموية نحو محور مركزي تقليدي وفي رواية سيرافيتا التي تعد رولية أخلاقية بما فيها من مساحة وارتفاع نجد نوعين اجتماعيين تقليديين يصطفان بحب نحو مخلث أوسط إن رواية فتلا مشربة بالعاطفة الجنسية الجنوبية ألتي يعاد صوغها في مخدع الماركيزة المترف أما رواية سيرافيناء هي تزد الجنس والجندر على جليد الشمال أي أن الجسد مقابل العقل والشهوانية مقابل التجريد مثل لورانس هه   يرسم بلزاك رسما بيائيا للفصام الثقافي الأوربي الطبيعة في حالة عبوديتها للملاك أو سيراف الجليد لا يتصدع والطبيعة لا تعش إلا عندما تستيقظ سيرافيتاء وتموت روايت بلزاك تختير وتصوب إحداهما الأخرى في نمط دائري من الجنس والجغرافيا",
    "label": 0,
    "confidence": 1.0
}