{
    "book_name": "خماسية مدن الملح",
    "page_number": 921,
    "text_chunk": "خلال الساعة التي قضنها في تبديل ملابسها والاهتمام بزينتها بدأ الضيوف يتوافدون أطلت من نافذة الخيمة فرأت زوجها يقف وسط مجموعة من الرجال ووجهه نحو الشرق عرفت بين الرجال سمير وراتب ولم تعرف ثلاثة آخرين اهتمت بسلمى عدلت لها باقة فستانها أكثر من مرة وسرحت خصلة الشعر المتدلية إلى الخلف على شكل ذيل حصانء فلما انتهت نظرت من النافذة مرة أخرى لاحظت أن عددا آخر من الضيوف قد وصل عرفت منهم مطيع وخلال دقائق بعد ذلك امتلأ المكان أمام الخيمة الوسطى بالرجال أحست بالقلق وبقليل من الخوف تريد أن ترى السلطان لحظة وصوله رأته مرة واحدة رأته وحده الآن تريد أن تراه وسط هذا الجمع تصورته قويا إلى درجة يثير الفزع وتصورت الرجال يتراكضون حوله تمنت لو تستطيع أن تسلم عليه أمام الجميع لو فعلت لاكتشف الرجال أنه يعرفهاء وأنها تعرفه وسوف يتساءلون ضحكت للفكرة واستبعدتها",
    "label": 0,
    "confidence": 1.0
}