{
    "book_name": "خماسية مدن الملح",
    "page_number": 1895,
    "text_chunk": "يلزم تعرف يا راكان وأنت يا مساعدء أن ما هو كل ما ينقال يصير زعلتم من كلمة وحتى هذه الكلمة قلناها من قبل وتذكرون أما ليش نقولها ونكررها نوبة ثانية هالحين فيلزم تعرفون الدنيا كلهاء من يوم ما صارت الحرب قائمة قاعدة تخلوا عن النظام في السلطنة لأنه لا يستحق الحماية إذ لا يمتلك الحد الأدنى من الشروط الإنسانية فهو إلى الآن لا يملك دستوراء ولا يعترف بأية حقوق للمواطنين إضافة إلى هذه سوالفهم في أميركاء في أوروباء بكل مكان وحنا يلزمنا ما نخاف تريدون دستور حلت البركة بس هالحين نريد عونكم ومساعدتكم وبعدما تخلص الحرب بعدما تتغير الأمور الله كريم",
    "label": 0,
    "confidence": 0.6666666666666666
}