{
    "book_name": "يوليسيس",
    "page_number": 826,
    "text_chunk": "ها لينتش يا أنت سجني ضمن العاطلين عن العمل شارع دينزل من هنا نغير هنا ليت الدعارة نحن الاثنان قالت نفعش عن نوم في بيت مريم غير المرخص ب حقاء كشيء سابن حميم دهم يغنون عالبا في أسرتهم أنأتي معنا أفى من هذا اللعين السخيم في لملابس السوداء أ اقترفوا الذنب بحق النور وحتى الآن إن ذلك اليوم قريب حينما يأني ليطهر العالم بالنار لتكمل الكتب المقدسة عن أغنية عندئذ تغلب طالب الطب دك على رفيقه طالب الطب ديفييا للشيطان من  استعمل بجويس ظواوه وهي كلمة إبرلندية دخلت في القاموس الاتكليزي  من أغنية للأطفال وكا ابوليس يخ بها السكارى من حيث قدرتهم على نطق  استعمل بجويس تمي عريا ال يحفظك  من أغنية لون لي وآدمز بعنران موواة  عن قصيدةالشاعر غابريال روسيني     امتموصاة اممصلق ع  استعمل جويس تيا لاتب أنظر كذذلك المزامير    أي البهود  الفكرة السيحية اليد عن يوم اقيمة هو أن العالأستلتهمه رتطهر تار  كتبها جويس بالف للاتنية أنظر كذلك بوحنائ    وازمور    قسم آخر من قصيدة أوليفر غوغارتي المعنرئةالمعتهداة لمعه عا لدمقوة وقيها بقارن",
    "label": 0,
    "confidence": 1.0
}