{
    "book_name": "رواية 1984",
    "page_number": 16,
    "text_chunk": "يقرب من للك تريخ  وكانث بي متداعية فالجفصين بتساقط من امن رائحة الملفوف جشا ونستو على ركبتيه وواج يتقخص كوع الأسقف والجدراا والأثيب تتنجر بفمل الصقيع والأسطح تسزب الأبوب كا يكرء اتعمال ييهء كم يكره الاتحاء لذ فلك يسبب له المي إلى الال مندما تله لشلرج وكا نظام التفة لا يعمل إل اتويات من السعالء يما كانت السيدة بارصون تظر ليه فظرة ةا بتصف طالعه هلا إذ لم يكم فاه كلية بدعرى العوفير ول قالت الو أن طوم كا مود لاسطاع أن يصلحها في لحظة الإسلاحات نيما عدا ثلك الثي بإمكان الساكن إنجازها بقب فكا امهوى القيام يمثل  أنه مام اليدين نعم إن طوع يجب أن ثمر معاملاتها عب لجا كانت تلكا في تفيذ أي شي حلى أن مكل  إصلاح لوح من الزجاج كان تفي يحتاج إلى سنتين ثم قالت السيفة بارصوق نستون في وزارة احقيق  لقد كاذ رجلا بارصون متظرة ها حصل كا لكي بسبب طياب طوم من اليه مالل للسمة شيط ولكن عليه علامات فياه مستحكم بل هو كتلة من",
    "label": 0,
    "confidence": 1.0
}