{
    "book_name": "اقنعة جنسية",
    "page_number": 782,
    "text_chunk": "للطبع والتي تستخدم بحرية لدى الجنودة وفي الصالون جميع العواطف والاتقعالات تأخذ الطابع الشهواني اللغة تحمل أكثر كي تعني أقل والسخرية الأخيرة في عبارة اشعر المرء بجنون في الداخل هي أن في الداخل قلبت معناها بسخرية محولة الذات إلى تعيين أو تحديد شهواني انتشائي للتحويل الخارجي الدنيوي فأن تكون في الداخل يعني ومن المفارقة أن تكون قد قفزت إلى مرثية هيراركية كلية إن الكتب والأفلام المصنوعة حول نجوم ونجماث هوليوود تتجذب نحو أسلوب مه لان مهنة النجم أو النجمة تقوم على الصورة على العرض الهيراركي واختلاط الخطوط البصرية أمام أعين جمهور واسع من المعجيين ففيلم كل شيء حول إيف لق  وطق للمخرج جوزيف ماتكفيتش  تعللمماة  طمعو  بنجومه الصاعدين والهابطين يتبني وعلى نحو تلقائي الفكاهة الوايلدية في النظرة إلى المخث الإنجليزي في مشهد الحفلة الصاخبة نجد بيني ديفيز في دور مارجو تشايج منمصمطن دجمهل تعثر على زوجها وهو يهلس مع ربيبتها التي لا تتورع عن فعل شيء ونراه يقول لها بخفة روح وفكاهة القد كنت أخبر إيف حول المرة التي نظرت فيه في الطرف الخطأ من لاقط الكاميرا رجعت ديفيز بسرعة مفاجنة مستشيطة غضباء وقبل أن ترحل أطلقت ملحة كارولية  نسبة إلى لويس كارول لانتسى أن تذكرني أن أحكي لك عن المرة التي نظرت فيها في قلب النخرشوفة في حفل كوكتيل يعد الخرشوف هو الشيء الوحيد الذي له قلب فوق المائدة الإخلاص أو الوجدان لا حقوق لهما على ذلك العالم المتحول إلى الخارج باتجاء أعيان الناس والنجوم إن الروح تقلصت إلى نسب افيتروفية للااة جديدة خاصة بإحدى المقبلات أو فاتح للشهية قلب الخرشوف في فيلم كل شيء حول إيف هو الرأس التافهء والقلب المتقلص وعند ألكسندر بوبه في الأشياء الصغيرة عداذدا تمنزل العراتس اللعبة في الصالون   ءهنا كتاب الحسد الأخضر للقلب الذي قامت بيتي ديفيز تفحصه بحنق وغضبه يشبه علية التبغ المنقوشة المقروءة بوقاحة من قبل ألجيرنون عند وايلد أوراق برونزية لحنكة مفتقدة ل  بعلا سما لظ ماعددماة   نسية إلى الرجل الفيتروقي وهي لوحة رسمها ليوناردو دا فينشي وثم رسمها على أساس أبعاد انان الال التي وضحها لمهتدس الروماني فيتوقيو والذي نسبت اللوحة إلى اسعه وهي تومز اي إلى السب الثابة بين أعضاء الإتسان الترجم ",
    "label": 0,
    "confidence": 1.0
}