{
    "book_name": "عداء الطائرة الورقية",
    "page_number": 140,
    "text_chunk": "أحيانا كنت أجلس خلف مقود الفورد أنزل التوافذ وأقود الساعات من الخليج الشرقي إلى الخليج الجنوبي  إلى أعلى يينيسولا وعودة قدت في الطريق الحددة بحقول القطن في حي فريمونت حيث أناس لم بصافحوا يوما ملوكاء عاشوا في ييوت مدقعة بالفقرء بنوافة مكسورة حي يتسرب من سياراته القديمة كسيارتي الزيت على الطرق السوداء أسيجة رمادية مغلقة على حدائق خلفية في حيناء ألعاب إطارات مهترئة وزجاجات بيرة محيت ماركاتها من القدم مرمية على مروج صغيرة غير منظمة  قدت بقرب حدائق بأشجار كبيرة تفوح منها رائحة البول وجانب متاجر كبيرة كفاية لتحوي خمس مسابقات بوزكاشي قدت التورينو إلى هضاب لوس ألتوس توقفت قرب أملاك بنوافذ ملوئة وأسود فضية تحمي البوابات بيوت بنوافير كبيرة ثزين الممرات ولا فورد تورينو بيوت تجعل من بيت باب في وزير أكبرخان يدو ككوخ الخدم   ",
    "label": 1,
    "confidence": 1.0
}