{
    "book_name": "خماسية مدن الملح",
    "page_number": 114,
    "text_chunk": "فواز الذي قضى في الحدرة سنة وبضعة شهور ما كادت تصله رسالة شعلان حتى دوت في رأسه تلك الأغنية القديمة السفر أما عندما تمثل له وادي العيون فلم يعد قادرا على الاحتمال أو الانتظار تدبر الأمر بسرعة وقرر أن يسافر مع أول قافلة وصويلح الابن الأوسط لسليمان الهديب لم يتردد ولم يطل استعداده ليكون جاهرا أما وضحة التي وافقت أسرع مما كان يتوقع الكثيرون فقد جعلت سليمان الهديب يشفق على هذا الصغير الذي يضيع كما ضاع أبوه وإذ حاول معه ليؤخر سفره في أن يذهب صويلح قبله حتى إذا وجد له عملا بعث وراءه لكن إزاء إصرار فوازء الذي بلغ جدود العناد وفي محاولة غامضة لإقامة رمز من نوع ما لهذه العائلة التي بدأت تتآكل وتضيع لم يطل الأمر وهكذا تأهب هذان الشابان للسفر على أن يعودا في أقرب وقت والا يتجاوزا وادي العيون كما أكد عليهما سليمان الهديب وكرر مرات كثيرة",
    "label": 0,
    "confidence": 1.0
}