{
    "book_name": "اقنعة جنسية",
    "page_number": 922,
    "text_chunk": "والعف وليس الجنس هو المبدأ الأقل اشتهاة للمنصر الديونيسوسي وسبق لي أن شددت على ذلك وهو ما يستبعده كل من روسوء ووردزورث وإمرسون من رؤيتهم اللطبيعة أما ديكنسون فهي مثل ساد تجذب القارئ نحو درجات تصاعدية من التوريط بداية من الإيروتيكية انتهاء بالاغتصاب والتشويه والقتل وهي مع إميلي برونتى تميطان اللثام عن العدرانية المكبوتة بفعل الإنساتية أو الانجاه الإنساني تقالأ ومن هناء فإن ديكنسون هي مبدعة القصائد السادية ولكنها أيضا مبدعة الساديين أنفسهم هؤلاء القراء الذين تلطخهم بدماء حملها    فعلى طريقة ملاك البصخة أو العبورء تلطخ ديكنسون عتبات المتزل البرجوازي برؤيتها الدموية فهي تعلن برضا القد كان موت في ليت المقابل منفاضية تماما عن القارئ الوردزورثي",
    "label": 0,
    "confidence": 0.6666666666666666
}