{
    "book_name": "بنات حواء الثلاث",
    "page_number": 122,
    "text_chunk": "كان منصور قد التقى في أيام شبابه طالبا من أوكسفوره مدن يحملون حقائيهم على ظهورهم وكان الرجل ممن يعرفون بالهبيين انحيل الجسم ممتقع الوجهء فشعر منصور من فوره بألفة ووئام تجاهه وكان هذا الرجل يخطط للسفر إلى تركيا بمفرده على متن دراجته وتباهى أنه يحتفظ بكل نقوده داخل جاربيه ليصد عنه النشالين ولصوص الفنادق وقد أصر منصور على مرافقته خشية أن يحدث شي ما لهذا الأجنبي الساذج وهكذا اجتاز الاثنان شبه جزيرة الأناضول مماء وبعدها عبر البريطاني الأشقر الشعر الحدود إلى إيران ولم يعرف منصور ماذا جرى لهء إلا أن لم ينس دهشته لرؤية بلده في عيون هذا المواطن الغربي وكانت المرة الأولى التي أدرك فيها أن ما يبدو اعتياديا اله قد لا يكون كذلك بالضرورة في عيون الغرباء وأدرك أول مرة أيضاا أن هناك عالما خارجياء وها هو الآن يريد أن يعلم ابنته هناك تلك رغبته الجامحة أن تنقذ بيري ومئات الشبان من أمثالهاء المتخرجين المتعلمين والمثاليين والتقدميين في تفكيرهم هذا البلد من تخلفه",
    "label": 0,
    "confidence": 1.0
}