{
    "book_name": "نظرية السياسة الخارجية",
    "page_number": 305,
    "text_chunk": "ءالمعل لال قل عق فق اق فك للح علج عرو لكو ع الا  القذافي   قسرارات السسياسة الخارجية طء   الف كلل وكل لامو كرو القالية للإحلال والسياسة الخارجية قابلية السياسات  القوات الجوية   الا  اللإحلال    القوة المسكرية المخمية بالتقيرة أن قا لل عن لفل نك فمن حمت لوم ممت عن لكر جد وجل عمل كفل لاقل مفلن رس كان الال لما م قرة الدولة افيف ككل عقن قل القابلية للإحسلال والتحسالف  لقب كيك قن فون كلل عت يبنا جو القابلية للإحلال وامعوئة الخارجية  قياس القيروالحفاظ  القوة المستمدة من حلقاء القسادةه لون إل لل فل لكل لال كف قلت الاي  كو كلل لفقل ككل مفلل  حمر محل لاحك عقر ينيد قازاقستان  القاعنة تتظيم    القسسرات  م ل لكر لكل فج كك قحف ق الان لا قف فق كنل كابول ككل ل   امم  كل كعد معد من عكر مكل  حكن تحر ملاو لصاح كح عير عفد كفل فك لوك لو عرو فاك جيون تمك الم عمل كي قار عمد عمر مقك مكل ملك كد كويساء   كت لوعت وتان م",
    "label": 0,
    "confidence": 0.6666666666666666
}