{
    "book_name": "خماسية مدن الملح",
    "page_number": 914,
    "text_chunk": "في مرحلة من المراحل اعتبر حماد أن كل ما حصل مجرد لعبة دبرها أحد نزلاء فندق الرابية ولا بد أن يكون هذا النزيل الغريب منافسا أو طامحاء وربما أراد أن يشوش على غزوان أمام الأميركيين بشكل خاص ولذلك فعل ما فعل هذا التفسير الذي توصل إليه أراحه بعض الوقت لكنه لم يزل الخوف من قلبه فهو الذي يعتبر نفسه ليس مسؤولا فقط عن أمن موران وإنما يهيئ نفسه منذ فترة لأن يكون أحد رجال قلائل مسؤولا عن أمن المنطقة كلها من الماء إلى الماء خاصة بعد أن أغدقت السلطنة بعطاياها على الكثيرين وربطت الكثيرين بأجهزتها أو بمصالح نجارية ومالية كبيرة ولأن حماد بالذات تزايدت روابط الصداقة والعلاقة التي تربطه بمسؤولي أجهزة الأمن في المنطقة",
    "label": 0,
    "confidence": 1.0
}