{
    "book_name": "سقوط الإمام",
    "page_number": 103,
    "text_chunk": "بنت الله مع الإمام ليلة العيد والفرح لم يكن هو اختياري ساقوني إليه في يدي سلسلة ومن حولي ثوب أبيض بلون أرواح الملائكة وكفن الموتىء وفي سسرير مزركش من الرخام الغالي كقبور الملكات وجدت نفسي عارية كما ولدتني أميء وتذكرت لم أ أمي منذ ولدت وفي بيت الأطفال كنت أمشي في النوم أبحث عن وجهها في الظلمة وفي الحلم أسمع صوت الله كصوت أمي يناديني فأجري إليه أعانقه أحتمي في صدره من أرواح الجان والشياطين وأنام الليل ولل معي وأصحو في الصباح ومعي اللسيح أحسه في أعماقي يتحرك بأرجل ناعمة كالقطيفة أحوطه بذراعي من تحت جدار البطن وأرفعه إلى أعلى تحت ضوء الشمس ليرا الله والوطن والإمام أبتسم في الوجوه والوجوه لا تبتسم تتقلب العيون داخل الجفون وتسقط الوجوه من فوق الرعوس وتصبح الرأس حمراء بقير شعر والوجه يفطيه الشعرء والصوت الناعم الحنون يصبح عواء الذثب يطاردني في النوم وأنا أشي في الظلمة أبحث عن أمي ومن خلفي أسمع الصوت يدوي كصوت الشيطان وأنا أجري وأقدام كثيرة من ورائي تجري ماثة قدم أو ألف كدبيب جيش لا يكف مائة يد أو آلف تمتد تضربني من الخلف وحين أستدير يهربون يخافون المواجهة وجها لوجه يخاف الواحد منهم أن يسير وحدهء لا يشعر بالقوة إلا وفي يده آلة قتل يسيرون على شكل صفوف متعرجة وسيقانهم متعرجة وعيونهم معوجة أعرفهم واحدا واحداء وأعرف وجه رئيسهم ووجوه كلابهم يرتدي الكلب في التهار وجه الحمل وفي الليل يرتدي وجه الذثي يسير الرجال في المقدمة ومن خلفهم الحراس ومن خلفهم الكلاب والقعلط يض تأتي تكشف عن أنيابهاء وتدب فوق الأرض بأقدام صغيرة مليئة باللحم خالية من العظم عيونها تلمع بالشبقء وبطونها منتفخة يملؤها الحرمان كالهواء الراكد في الغرف المفلقة",
    "label": 1,
    "confidence": 1.0
}