{
    "book_name": "سقوط الإمام",
    "page_number": 141,
    "text_chunk": "العشيقة جاءت من بيت السعادة ثلقي عليه نظرة أخيرة وهو راقد يبتسم في الصندوق ينظر إليها وفي عينيه بريق العشق قالت نزوة يائسة أخيرة لا تفعل شيثا وعشقه للنساء كمحاولاته اليائسة مع الفشل دخلت واقفة تحوط رأسها بشعرها الكثيف تربطه بمنديل أبيض يتدق منه الترترء وحوات بصرها عنه إلى زوجاته الشرعيات واقفات يرتدين ملابس الجداد وجوههن متشابهة وأياديهن الصغيرة البشة معقودة فوق قلوبهن وأنفاسهن مكتومة وسيقاتهن فوق الكعوب الرفيعة ملتصقة ولا تكاد تفرق الواحدة عن الأخرى إلا بدبوس فوق الصدر أو شارة على الكتف واللامح ممسوحة والرأس صفير والريف اثقيلء والروح غائبة واقفات صامتات ينظرن إليها بعيون جاحظة كعيون الضفادع أو السمك تحت اماء وانفرجت الشفاه الطبقة في آن واحد وسألن من أنت قالت وهي ترفع رأسها فوق عنقها بحركة كالشمخة لم تعرفها الزوجات الشرعيات أنا العشيقة جواهر وارتجت أجسادهن فوق الكعوب الرفيعة ومع ارتجاجة الجسد عادت الروح ومعها الوعي ورأين في عيتيها السوداوين بريقا موجعا كالصدق اخترق عيونهنء ونفذ رغم الوجع إلى بؤرة في القلب وهتفن بصوت واحد عشيقة من فيهم قالت كلهم ابتدا من الإمام إلى حارس القبة وامتارة وانسعت عيونهن بذعر أخفينها تحت الايديء والتقت الأذرع حول الصدور تحكم إغلاق القوقعة وهتفن بصوت كاللهاث أنت الشيطان وعقابك الموت وأطلقن سيقانهن السمينة للريح والكعوب المدبية تطرقع كالصواريخ ولم يبق في الغرفة إلا اثنان الزوجة الأخيرة والابنة غير الشرعية واقفتان والآيدي متشابكة وامتدت إليهما يد العشيقة والتقت الثلاث في عناق تشابكت الأذرع الست فوق الجسد الراقد في الصندوق والابتسامة فوق شفتيه راحت وملامح الوجه تلاشت لم يعد يشبه وجه الإمام ولا الكاتب الكبير ولا رئيس الأمن ولا العارض الشرعيء ولا أي رجل من حزب الله أو الشيطان أصبح",
    "label": 0,
    "confidence": 1.0
}