{
    "book_name": "يوليسيس",
    "page_number": 1054,
    "text_chunk": "حارة أو  أومليت على بطن قطعة من شيكسير يللا تدق على بطنها وانسدحت إلى الوراء على الأريكة مع صيحة ضحك أومليت  على ها هرا ها هؤ أومليت على سيفن لبأناقة متكلفة أحبك يا سيدتي الحبيبة أنكلم معك باللسان الانكليزي من أجل نفاهم ودي مضاعفآ نعي أيها الرجل المنعزل كم تكلف هزيمة ووثرلوا كيف يتوقف فجبأة ويرفع سبابتة ينلا ضاحكة أومليت المومسات اضاحكات أعذ ثانية اعد ثانية سيفن إصغوا لي  حلمت بيطيخةل  تعن بالفرنسية مسحية لشيكسيو ولكن ما دامت مك علي أيضا أي من لذ يكون معنى التورية قطعة من شيكسبير  كتبها جويس باللغة الفرنسية  الهزمة الت تبي بها تايرث في  نيو عام  ادها من مماءعند فتعني المرحاض في العامية المريطائية  راجع اخلقة لاه    داطامد ندا ودماه مثااتيو",
    "label": 0,
    "confidence": 1.0
}