{
    "book_name": "اقنعة جنسية",
    "page_number": 803,
    "text_chunk": "في إحدى محادثاته احياة المدينة تغذي وتكمل كل العناصر الأكثر تحضرا في الرجل والجتلمان لا ينظر أبنا من النافذة وعندما قام وايلد وبضغط من مخرجه وبتعجل بقص مسرحية أهمية أن تكون جاداء إلى ثلاثة فصول قام بعمل تغييرات عديدة مؤسفة في المواقع فمشهد طاولة الشاي كان في الأصل يدور داخل المرسم وليس في الحديقة والمرسمء هو المكان الصحيح المناسب لهذا المشهد فهو صالون القرن الثامن عشر بما يمتاز به من خنوثة الأسلوب وقد دمرت المراجمات أبضا واحدة من الإخراجات المسرحية الأكثر سخرية في الدراما الإنجليزية في المسرحية تبدأ الحرب بين الجنسين أصكا بمغادرة النساء فهن ينعزلن باتجاه الحديقة بنظرات ساخرة هذا السطر الرائع يمد في مناهضة وايلد للطبيعة أبعد من هدفه المباشرء وهو وردزورث ليشمل كل الشعر الإنجليزي عائنا إلى عذراوات وحدائق سبنسرء وفجأة تدخلان دون  ومارفل  حوريتا سبنسر الأختان الجميلتان وهما مقطيناالجبين إلى مرج أقل بهجة الإخراج المسرحي هنا",
    "label": 0,
    "confidence": 0.6666666666666666
}