{
    "book_name": "نقد العقل العربي",
    "page_number": 380,
    "text_chunk": "ابوطويا إضوك الصف حذر نفدي وبلا إعادة دراسة معمقة للملف الإخواني على المصادرة الإسماعيلية لصك ملكية ترائهم  وبانتظار أن يعاد فتح الملف الإخواني وتحريره  بفضل مناهج حفريات المعرفة  من خناق الهوى الأبديولوجي فإننا قد تغامر هنا بتقديم تعليل إضافي للفشل التاريخي لإخوان الصفاء كفريق عمل جماعي فمن يقرأ رسائل الإخوان ويعيد قراءتها بتمعن يمكنه أن يلاحظ بعض الاختلاف في صياغة مصنفي الرسائل للإشكالية المركزية الإخوانية إشكالية التوفيق بين الشريعة والفلسفة فقد كنا رأينا مصف ليالي الإمتاع والمؤانسة يؤكد أن الهدف الذي اجتمعت عليه العصبة الأخوائية هو فسل الشريعة وتطهيرها بالفلسفة بعد أن دنست بالجهالات واختلطت بالضلالات ويموجب هنا التشخيص يكون المريض هو الشريعة والطبيب هو الفلسقة وهذا التقديم اللفلسقة في الصحةء وهذا التأخير للشريعة في المرض هو ما يؤكده أيضا المفدسي المحرر الأول للرسائل فيما يبدوء حيث اندفع يقول وقد هيجه الحريري غلام ابن طراره يوما في الوراقين الشريعة طب المرضى والفلسقة طب الأصحاء والأنبياء يطون للمرضى حتى لا يتزايد مرضهم والفلسفة طب الأصحاء   والقلاسفة يحقظون الصحة على أصحابها حتى لا يعتريهم مرض أصلا والحال أن رسائل إخوان الصفاء كما وصلتنا ل نتساوى كلها فيما بينها في هذا الإخراج الجريء لإشكالية التوفيق بين الشريعة والفلسفة فهناك من الرسائل ما يعيد التوكيد على أن المذاهب والديانات كلها وضعت كالعقاقير والأدوية والأشربة لمرضى النفوس وأن الأنبياء هم أطباء النفوسي وهناك من الرسائل ما يضع الشريعة والفلسفة على قدم من المساواة في المصدر كما في المقصد اعلم أن العلوم الحكمية والشريعة النبوية كلاهما أمران إلهيان يتفقان في الغرض ا ارسج ا ص فلوج ان ص  ",
    "label": 0,
    "confidence": 1.0
}